change_point_algorithms.libs/libgcc_s-98a1ef30.so.1
change_point_algorithms/__init__.py
change_point_algorithms/_change_point_algorithms.cpython-312-x86_64-linux-musl.so
change_point_algorithms/_change_point_algorithms.pyi
change_point_algorithms/online_detection/__init__.py
change_point_algorithms/online_detection/bocpd.py
change_point_algorithms/online_detection/cusum.py
change_point_algorithms/online_detection/expect_Max.py
change_point_algorithms/online_detection/grey_systems_model.py
change_point_algorithms/online_detection/model_helpers.py
change_point_algorithms/py.typed
online_changepoint_algorithms-0.0.1.dist-info/METADATA
online_changepoint_algorithms-0.0.1.dist-info/WHEEL
online_changepoint_algorithms-0.0.1.dist-info/licenses/LICENSE
online_changepoint_algorithms-0.0.1.dist-info/RECORD
